texer/__init__.py
texer/eval.py
texer/pgfplots.py
texer/specs.py
texer/tables.py
texer/utils.py
texer-0.5.12.dist-info/licenses/LICENSE
texer-0.5.12.dist-info/METADATA
texer-0.5.12.dist-info/WHEEL
texer-0.5.12.dist-info/top_level.txt
texer-0.5.12.dist-info/RECORD
